<annotation>
	<folder>2018-04-01_1_3</folder>
	<filename>image131.bmp</filename>
	<path>/home/morten/catkin_ws/src/r18dv_cone_detection/scripts/images/2018-04-01_1_3/image131.bmp</path>
	<source>
		<database>Unknown</database>
	</source>
	<size>
		<width>648</width>
		<height>488</height>
		<depth>3</depth>
	</size>
	<segmented>0</segmented>
	<object>
		<name>cone-small-blue</name>
		<pose>Unspecified</pose>
		<truncated>0</truncated>
		<difficult>0</difficult>
		<bndbox>
			<xmin>125</xmin>
			<ymin>340</ymin>
			<xmax>159</xmax>
			<ymax>384</ymax>
		</bndbox>
	</object>
	<object>
		<name>cone-small-blue</name>
		<pose>Unspecified</pose>
		<truncated>0</truncated>
		<difficult>0</difficult>
		<bndbox>
			<xmin>164</xmin>
			<ymin>305</ymin>
			<xmax>183</xmax>
			<ymax>331</ymax>
		</bndbox>
	</object>
	<object>
		<name>cone-small-blue</name>
		<pose>Unspecified</pose>
		<truncated>0</truncated>
		<difficult>0</difficult>
		<bndbox>
			<xmin>272</xmin>
			<ymin>284</ymin>
			<xmax>285</xmax>
			<ymax>301</ymax>
		</bndbox>
	</object>
	<object>
		<name>cone-small-blue</name>
		<pose>Unspecified</pose>
		<truncated>0</truncated>
		<difficult>0</difficult>
		<bndbox>
			<xmin>150</xmin>
			<ymin>280</ymin>
			<xmax>163</xmax>
			<ymax>295</ymax>
		</bndbox>
	</object>
	<object>
		<name>cone-small-blue</name>
		<pose>Unspecified</pose>
		<truncated>0</truncated>
		<difficult>0</difficult>
		<bndbox>
			<xmin>73</xmin>
			<ymin>292</ymin>
			<xmax>87</xmax>
			<ymax>312</ymax>
		</bndbox>
	</object>
	<object>
		<name>cone-small-yellow</name>
		<pose>Unspecified</pose>
		<truncated>0</truncated>
		<difficult>0</difficult>
		<bndbox>
			<xmin>27</xmin>
			<ymin>280</ymin>
			<xmax>41</xmax>
			<ymax>297</ymax>
		</bndbox>
	</object>
	<object>
		<name>cone-small-yellow</name>
		<pose>Unspecified</pose>
		<truncated>0</truncated>
		<difficult>0</difficult>
		<bndbox>
			<xmin>512</xmin>
			<ymin>358</ymin>
			<xmax>551</xmax>
			<ymax>416</ymax>
		</bndbox>
	</object>
	<object>
		<name>cone-small-yellow</name>
		<pose>Unspecified</pose>
		<truncated>0</truncated>
		<difficult>0</difficult>
		<bndbox>
			<xmin>558</xmin>
			<ymin>314</ymin>
			<xmax>583</xmax>
			<ymax>346</ymax>
		</bndbox>
	</object>
	<object>
		<name>cone-small-yellow</name>
		<pose>Unspecified</pose>
		<truncated>0</truncated>
		<difficult>0</difficult>
		<bndbox>
			<xmin>424</xmin>
			<ymin>291</ymin>
			<xmax>439</xmax>
			<ymax>312</ymax>
		</bndbox>
	</object>
</annotation>
