<annotation>
	<folder>2018-04-01_1_7</folder>
	<filename>image311.bmp</filename>
	<path>C:\Users\Didrik\Documents\Labeling\2018-04-01_1_7\image311.bmp</path>
	<source>
		<database>Unknown</database>
	</source>
	<size>
		<width>648</width>
		<height>488</height>
		<depth>3</depth>
	</size>
	<segmented>0</segmented>
	<object>
		<name>cone-small-yellow</name>
		<pose>Unspecified</pose>
		<truncated>0</truncated>
		<difficult>0</difficult>
		<bndbox>
			<xmin>441</xmin>
			<ymin>361</ymin>
			<xmax>493</xmax>
			<ymax>420</ymax>
		</bndbox>
	</object>
	<object>
		<name>cone-small-yellow</name>
		<pose>Unspecified</pose>
		<truncated>0</truncated>
		<difficult>0</difficult>
		<bndbox>
			<xmin>306</xmin>
			<ymin>296</ymin>
			<xmax>324</xmax>
			<ymax>322</ymax>
		</bndbox>
	</object>
	<object>
		<name>cone-small-yellow</name>
		<pose>Unspecified</pose>
		<truncated>0</truncated>
		<difficult>0</difficult>
		<bndbox>
			<xmin>202</xmin>
			<ymin>281</ymin>
			<xmax>217</xmax>
			<ymax>297</ymax>
		</bndbox>
	</object>
	<object>
		<name>cone-small-yellow</name>
		<pose>Unspecified</pose>
		<truncated>0</truncated>
		<difficult>0</difficult>
		<bndbox>
			<xmin>100</xmin>
			<ymin>279</ymin>
			<xmax>112</xmax>
			<ymax>293</ymax>
		</bndbox>
	</object>
</annotation>
