<annotation>
	<folder>2018-04-01_1_5</folder>
	<filename>image231.bmp</filename>
	<path>C:\Users\Didrik\Documents\Labeling\2018-04-01_1_5\image231.bmp</path>
	<source>
		<database>Unknown</database>
	</source>
	<size>
		<width>648</width>
		<height>488</height>
		<depth>3</depth>
	</size>
	<segmented>0</segmented>
	<object>
		<name>cone-small-yellow</name>
		<pose>Unspecified</pose>
		<truncated>0</truncated>
		<difficult>0</difficult>
		<bndbox>
			<xmin>532</xmin>
			<ymin>367</ymin>
			<xmax>594</xmax>
			<ymax>432</ymax>
		</bndbox>
	</object>
	<object>
		<name>cone-small-yellow</name>
		<pose>Unspecified</pose>
		<truncated>0</truncated>
		<difficult>0</difficult>
		<bndbox>
			<xmin>351</xmin>
			<ymin>318</ymin>
			<xmax>381</xmax>
			<ymax>353</ymax>
		</bndbox>
	</object>
	<object>
		<name>cone-small-blue</name>
		<pose>Unspecified</pose>
		<truncated>0</truncated>
		<difficult>0</difficult>
		<bndbox>
			<xmin>221</xmin>
			<ymin>306</ymin>
			<xmax>244</xmax>
			<ymax>332</ymax>
		</bndbox>
	</object>
</annotation>
